pybrot/ComplexDraw.py
pybrot/Examples.py
pybrot/MandelColoring.py
pybrot/Mandelbrot.py
pybrot/__init__.py
pybrot-0.0.7.dist-info/METADATA
pybrot-0.0.7.dist-info/RECORD
pybrot-0.0.7.dist-info/WHEEL
pybrot-0.0.7.dist-info/top_level.txt
