Metadata-Version: 2.1
Name: pybrot
Version: 0.0.7
Summary: A python package to create mandelbrot set images.
Home-page: https://github.com/teunvw14/pybrot
Author: Teun van Wezel
Author-email: vanwezelteun@gmail.com
License: UNKNOWN
Platform: UNKNOWN
Classifier: Programming Language :: Python :: 3
Classifier: Operating System :: OS Independent
